atoti_query/__init__.py
atoti_query/_arrow_to_pandas.py
atoti_query/_cellset.py
atoti_query/_cellset_to_query_result.py
atoti_query/_content_client.py
atoti_query/_create_query_cubes_from_discovery.py
atoti_query/_cube_discovery.py
atoti_query/_execute_gaq.py
atoti_query/_gaq_filter.py
atoti_query/_generate_mdx.py
atoti_query/_get_data_types.py
atoti_query/_internal/__init__.py
atoti_query/_is_gaq_filter.py
atoti_query/_mdx_ast.py
atoti_query/_parse_level_identifier.py
atoti_query/_query_mdx.py
atoti_query/_query_private_parameters.py
atoti_query/_query_result_metadata.py
atoti_query/_stringify_mdx.py
atoti_query/_widget_conversion_details.py
atoti_query/auth.py
atoti_query/basic_authentication.py
atoti_query/client_certificate.py
atoti_query/oauth2_resource_owner_password_authentication.py
atoti_query/py.typed
atoti_query/query_cube.py
atoti_query/query_cubes.py
atoti_query/query_hierarchies.py
atoti_query/query_hierarchy.py
atoti_query/query_level.py
atoti_query/query_levels.py
atoti_query/query_measure.py
atoti_query/query_measures.py
atoti_query/query_result.py
atoti_query/query_session.py
atoti_query/security/__init__.py
atoti_query/security/_authentication_type.py
atoti_query/security/_column_key.py
atoti_query/security/_constants.py
atoti_query/security/_restriction.py
atoti_query/security/_restriction_from_mapping.py
atoti_query/security/_restriction_to_dict.py
atoti_query/security/_restrictions.py
atoti_query/security/_roles.py
atoti_query/security/_service.py
atoti_query/security/basic_security.py
atoti_query/security/default_roles.py
atoti_query/security/individual_roles.py
atoti_query/security/kerberos_security.py
atoti_query/security/ldap_security.py
atoti_query/security/oidc_security.py
atoti_query/security/role_mapping.py
atoti_query/security/security.py
atoti_query/token_authentication.py
atoti_query-0.8.14.dist-info/METADATA
atoti_query-0.8.14.dist-info/WHEEL
atoti_query-0.8.14.dist-info/RECORD
