Metadata-Version: 2.1
Name: atoti-query
Version: 0.8.14
Summary: Package to query Atoti sessions
Home-page: https://www.atoti.io
License: Proprietary
Keywords: atoti,query
Author: ActiveViam
Author-email: dev@atoti.io
Requires-Python: >=3.9
Classifier: Development Status :: 4 - Beta
Classifier: License :: Free To Use But Restricted
Classifier: License :: Other/Proprietary License
Classifier: Operating System :: OS Independent
Classifier: Programming Language :: Python :: 3
Classifier: Programming Language :: Python :: 3.9
Classifier: Programming Language :: Python :: 3.10
Classifier: Programming Language :: Python :: 3.11
Classifier: Programming Language :: Python :: 3.12
Classifier: Typing :: Typed
Requires-Dist: atoti-core (==0.8.14)
Requires-Dist: pandas (>=1.5.3)
Requires-Dist: pyarrow (>=15.0.2)
Requires-Dist: pydantic (>=2.6.0)
Requires-Dist: typing-extensions (>=4.6.1)
Project-URL: Bug Tracker, https://github.com/atoti/atoti/issues
Project-URL: Documentation, https://docs.atoti.io/0.8.14/api/atoti_query.html
